flappy/Face.py
flappy/Flappy.py
flappy/LandingPage.py
flappy/UserForm.py
flappy/__init__.py
ARFlappy-0.1.0.dist-info/METADATA
ARFlappy-0.1.0.dist-info/WHEEL
ARFlappy-0.1.0.dist-info/top_level.txt
ARFlappy-0.1.0.dist-info/RECORD
